rich_toolkit/__init__.py
rich_toolkit/_getchar.py
rich_toolkit/_input_handler.py
rich_toolkit/_rich_components.py
rich_toolkit/button.py
rich_toolkit/container.py
rich_toolkit/element.py
rich_toolkit/form.py
rich_toolkit/input.py
rich_toolkit/menu.py
rich_toolkit/progress.py
rich_toolkit/py.typed
rich_toolkit/spacer.py
rich_toolkit/toolkit.py
rich_toolkit/styles/__init__.py
rich_toolkit/styles/base.py
rich_toolkit/styles/border.py
rich_toolkit/styles/fancy.py
rich_toolkit/styles/minimal.py
rich_toolkit/styles/tagged.py
rich_toolkit/utils/__init__.py
rich_toolkit/utils/colors.py
rich_toolkit/utils/map_range.py
rich_toolkit-0.18.0.dist-info/METADATA
rich_toolkit-0.18.0.dist-info/WHEEL
rich_toolkit-0.18.0.dist-info/licenses/LICENSE
rich_toolkit-0.18.0.dist-info/licenses/LICENSE-THIRD-PARTY
rich_toolkit-0.18.0.dist-info/RECORD
