Metadata-Version: 2.4
Name: rich-toolkit
Version: 0.18.0
Summary: Rich toolkit for building command-line applications
License-Expression: MIT
License-File: LICENSE
License-File: LICENSE-THIRD-PARTY
Classifier: Development Status :: 4 - Beta
Classifier: Intended Audience :: Developers
Classifier: License :: OSI Approved :: MIT License
Classifier: Topic :: Software Development :: Libraries
Classifier: Topic :: Software Development :: Libraries :: Python Modules
Requires-Python: >=3.8
Requires-Dist: click>=8.1.7
Requires-Dist: rich>=13.7.1
Requires-Dist: typing-extensions>=4.12.2
